dwdpollen/__init__.py
dwdpollen-0.1.0.dist-info/LICENSE
dwdpollen-0.1.0.dist-info/METADATA
dwdpollen-0.1.0.dist-info/WHEEL
dwdpollen-0.1.0.dist-info/top_level.txt
dwdpollen-0.1.0.dist-info/RECORD
