Metadata-Version: 2.1
Name: dwdpollen
Version: 0.1.0
Summary: API client for the "Deutscher Wetterdienst" to get the current pollen load in Germany
Home-page: https://github.com/ekeih/dwdpollen
Author: Max Rosin
Author-email: git@hackrid.de
License: UNKNOWN
Platform: UNKNOWN
Classifier: Programming Language :: Python :: 3
Classifier: License :: OSI Approved :: GNU General Public License v3 or later (GPLv3+)
Classifier: Operating System :: OS Independent
Requires-Dist: requests
Requires-Dist: pytz
